klotty/__init__.py
klotty/api.py
klotty/exceptions.py
klotty/version.py
klotty-0.1.0.dist-info/LICENSE.md
klotty-0.1.0.dist-info/METADATA
klotty-0.1.0.dist-info/WHEEL
klotty-0.1.0.dist-info/top_level.txt
klotty-0.1.0.dist-info/RECORD
