Metadata-Version: 2.1
Name: klotty
Version: 0.1.0
Summary: Klotty Python SDK
Home-page: https://github.com/drish/klotty-py
Author: Derich Pacheco
Author-email: carlosderich@gmail.com
Keywords: email,email platform
Classifier: Development Status :: 4 - Beta
Classifier: Intended Audience :: Developers
Classifier: License :: OSI Approved :: MIT License
Classifier: Natural Language :: English
Classifier: Operating System :: OS Independent
Classifier: Programming Language :: Python :: 3
Classifier: Programming Language :: Python :: 3.7
Classifier: Programming Language :: Python :: 3.8
Classifier: Programming Language :: Python :: 3.9
Classifier: Programming Language :: Python :: 3.10
Requires-Python: >3.7.5
License-File: LICENSE.md
Requires-Dist: requests
